sentinel/README.md
sentinel/__init__.py
sentinel/cli/__init__.py
sentinel/cli/main.py
sentinel/core/__init__.py
sentinel/core/context.py
sentinel/core/engine.py
sentinel/core/finding.py
sentinel/core/pipeline.py
sentinel/engines/__init__.py
sentinel/engines/adapter.py
sentinel/engines/example_injection.py
sentinel/hooks/__init__.py
sentinel/hooks/manager.py
sentinel/hooks/spec.py
sentinel/integrations/__init__.py
sentinel/integrations/fastapi.py
sentinel_llm_security-1.0.0.dist-info/METADATA
sentinel_llm_security-1.0.0.dist-info/WHEEL
sentinel_llm_security-1.0.0.dist-info/entry_points.txt
sentinel_llm_security-1.0.0.dist-info/licenses/LICENSE
sentinel_llm_security-1.0.0.dist-info/RECORD
