Metadata-Version: 2.4
Name: sentinel-llm-security
Version: 1.0.0
Summary: AI Security Framework — The pytest of AI Security
Project-URL: Homepage, https://github.com/yourusername/sentinel-ai
Project-URL: Documentation, https://sentinel-ai.readthedocs.io
Project-URL: Repository, https://github.com/yourusername/sentinel-ai
Project-URL: Issues, https://github.com/yourusername/sentinel-ai/issues
Author: SENTINEL Team
License-Expression: MIT
License-File: LICENSE
Keywords: ai-security,guardrails,jailbreak-detection,llm-security,penetration-testing,prompt-injection,red-team
Classifier: Development Status :: 4 - Beta
Classifier: Intended Audience :: Developers
Classifier: Intended Audience :: Science/Research
Classifier: License :: OSI Approved :: MIT License
Classifier: Operating System :: OS Independent
Classifier: Programming Language :: Python :: 3
Classifier: Programming Language :: Python :: 3.9
Classifier: Programming Language :: Python :: 3.10
Classifier: Programming Language :: Python :: 3.11
Classifier: Programming Language :: Python :: 3.12
Classifier: Topic :: Scientific/Engineering :: Artificial Intelligence
Classifier: Topic :: Security
Requires-Python: >=3.9
Requires-Dist: aiohttp>=3.8
Requires-Dist: pydantic>=2.0
Provides-Extra: cli
Requires-Dist: click>=8.0; extra == 'cli'
Requires-Dist: rich>=13.0; extra == 'cli'
Provides-Extra: dev
Requires-Dist: black>=23.0; extra == 'dev'
Requires-Dist: flake8>=6.0; extra == 'dev'
Requires-Dist: mypy>=1.0; extra == 'dev'
Requires-Dist: pytest-asyncio>=0.21; extra == 'dev'
Requires-Dist: pytest>=7.0; extra == 'dev'
Provides-Extra: full
Requires-Dist: sentinel-ai[cli,ml,plugins]; extra == 'full'
Provides-Extra: ml
Requires-Dist: sentence-transformers>=2.2; extra == 'ml'
Requires-Dist: torch>=2.0; extra == 'ml'
Requires-Dist: transformers>=4.30; extra == 'ml'
Provides-Extra: plugins
Requires-Dist: pluggy>=1.0; extra == 'plugins'
